feynplots/__init__.py
feynplots/main.py
feynplots-1.1.1.dist-info/LICENSE
feynplots-1.1.1.dist-info/METADATA
feynplots-1.1.1.dist-info/WHEEL
feynplots-1.1.1.dist-info/top_level.txt
feynplots-1.1.1.dist-info/RECORD
