Metadata-Version: 2.1
Name: feynplots
Version: 1.1.1
Summary: Plotting Feyn graphs
Home-page: https://github.com/chriscave/cave-plots
Author: Chris Cave
Author-email: chris.cave@abzu.ai
License: MIT
Platform: UNKNOWN
Requires-Dist: feyn (==1.2.*)
Requires-Dist: numpy (>=1.18.1)
Requires-Dist: matplotlib (>=3.1.3)
